odoo8_addon_l10n_it_pec-8.0.0.1.0.99.dev4-py2.7-nspkg.pth
odoo8_addon_l10n_it_pec-8.0.0.1.0.99.dev4.dist-info/DESCRIPTION.rst
odoo8_addon_l10n_it_pec-8.0.0.1.0.99.dev4.dist-info/METADATA
odoo8_addon_l10n_it_pec-8.0.0.1.0.99.dev4.dist-info/RECORD
odoo8_addon_l10n_it_pec-8.0.0.1.0.99.dev4.dist-info/WHEEL
odoo8_addon_l10n_it_pec-8.0.0.1.0.99.dev4.dist-info/metadata.json
odoo8_addon_l10n_it_pec-8.0.0.1.0.99.dev4.dist-info/namespace_packages.txt
odoo8_addon_l10n_it_pec-8.0.0.1.0.99.dev4.dist-info/top_level.txt
odoo_addons/l10n_it_pec/AUTHORS.txt
odoo_addons/l10n_it_pec/__init__.py
odoo_addons/l10n_it_pec/__openerp__.py
odoo_addons/l10n_it_pec/i18n/es.po
odoo_addons/l10n_it_pec/i18n/it.po
odoo_addons/l10n_it_pec/i18n/l10n_it_pec.pot
odoo_addons/l10n_it_pec/i18n/sl.po
odoo_addons/l10n_it_pec/model/__init__.py
odoo_addons/l10n_it_pec/model/partner.py
odoo_addons/l10n_it_pec/static/description/icon.png
odoo_addons/l10n_it_pec/view/partner_view.xml
